README.txt
setup.cfg
setup.py
zopeskel.txt
docs/HISTORY.txt
docs/INSTALL.txt
docs/LICENSE.GPL
docs/LICENSE.txt
iw/__init__.py
iw.plonepatches.egg-info/PKG-INFO
iw.plonepatches.egg-info/SOURCES.txt
iw.plonepatches.egg-info/dependency_links.txt
iw.plonepatches.egg-info/entry_points.txt
iw.plonepatches.egg-info/namespace_packages.txt
iw.plonepatches.egg-info/not-zip-safe
iw.plonepatches.egg-info/requires.txt
iw.plonepatches.egg-info/top_level.txt
iw/plonepatches/__init__.py
iw/plonepatches/configure.zcml
iw/plonepatches/pts.py
iw/plonepatches/tests.py