Metadata-Version: 1.0
Name: iw.plonepatches
Version: 0.1.0
Summary: Patches for Plone 3.x
Home-page: https://ingeniweb.svn.sourceforge.net/svnroot/ingeniweb/iw.plonepatches
Author: Ingeniweb
Author-email: support@ingeniweb.com
License: GPL
Platform: UNKNOWN
Classifier: Framework :: Plone
Classifier: Programming Language :: Python
Classifier: Topic :: Software Development :: Libraries :: Python Modules
